{
  "base_url": "https://hogak.live",
  "requires_auth": false,
  "_meta": {
    "ScenarioID": "AUTH-03",
    "구분": "회원/인증",
    "우선순위": "P0",
    "시나리오명": "전화번호(SMS) 인증 포함 가입",
    "목적/범위": "SMS 본인확인 기반 가입 플로우 검증",
    "사전조건": "비회원, SMS 수신 가능한 번호",
    "테스트데이터": "테스트 전화번호(실 SMS/가상번호)",
    "Steps(원문)": "1) 가입 시작 → 전화번호 입력\n2) 인증번호 발송\n3) 인증번호 입력(성공)\n4) 가입 완료",
    "기대결과": "인증 성공 시 가입 진행, 실패 시 재시도/제한 정책 적용",
    "연동시스템": "SMS",
    "검증/로그 포인트": "재전송 제한/쿨다운/횟수 제한 로그",
    "TODO/확인필요": "__TODO__ 인증번호 재전송/제한 정책 확인"
  },
  "steps": [
    {
      "type": "go",
      "url": "https://hogak.live/main",
      "delay_ms": 1200
    },
    {
      "type": "wait_visible",
      "text": "경기일정",
      "timeout": 15000
    },
    {
      "type": "screenshot",
      "name": "AUTH-03_final"
    }
  ]
}
